{
  "local": {
    "Sedan_Hail_Day": {
      "levy": 1.32,
      "flagfall": 5,
      "booking_fee": 0,
      "cutoff_km": 12,
      "rate_short": 2.52,
      "rate_long": 2.29
    },
    "Sedan_Hail_Night": {
      "levy": 1.32,
      "flagfall": 5,
      "booking_fee": 0,
      "cutoff_km": 12,
      "rate_short": 3,
      "rate_long": 2.73
    },
    "Maxi_Hail_Day": {
      "levy": 1.32,
      "flagfall": 7.5,
      "booking_fee": 0,
      "cutoff_km": 12,
      "rate_short": 3.78,
      "rate_long": 3.435
    },
    "Maxi_Hail_Night": {
      "levy": 1.32,
      "flagfall": 7.5,
      "booking_fee": 0,
      "cutoff_km": 12,
      "rate_short": 4.5,
      "rate_long": 4.095
    },
    "Sedan_Booking_Day": {
      "levy": 1.32,
      "flagfall": 5,
      "booking_fee": 5,
      "cutoff_km": 5,
      "rate_short": 3.52,
      "rate_long": 2.52
    },
    "Sedan_Booking_Night": {
      "levy": 1.32,
      "flagfall": 5,
      "booking_fee": 5,
      "cutoff_km": 5,
      "rate_short": 4,
      "rate_long": 3
    },
    "Maxi_Booking_Day": {
      "levy": 1.32,
      "flagfall": 7.5,
      "booking_fee": 5,
      "cutoff_km": 5,
      "rate_short": 4.78,
      "rate_long": 3.435
    },
    "Maxi_Booking_Night": {
      "levy": 1.32,
      "flagfall": 11.34,
      "booking_fee": 5,
      "cutoff_km": 5,
      "rate_short": 5.5,
      "rate_long": 4.095
    }
  },
  "long_distance": {
    "20": { "Day": 82.0, "Night": 101.0, "Corp": 109.0 },
    "25": { "Day": 99.0, "Night": 123.0, "Corp": 133.0 },
    "30": { "Day": 116.0, "Night": 144.0, "Corp": 157.0 },
    "35": { "Day": 134.0, "Night": 166.0, "Corp": 181.0 },
    "40": { "Day": 151.0, "Night": 188.0, "Corp": 205.0 },
    "45": { "Day": 168.0, "Night": 210.0, "Corp": 228.0 },
    "50": { "Day": 185.0, "Night": 232.0, "Corp": 252.0 },
    "55": { "Day": 202.0, "Night": 254.0, "Corp": 276.0 },
    "60": { "Day": 220.0, "Night": 275.0, "Corp": 300.0 },
    "65": { "Day": 237.0, "Night": 297.0, "Corp": 324.0 },
    "70": { "Day": 254.0, "Night": 319.0, "Corp": 348.0 },
    "75": { "Day": 271.0, "Night": 341.0, "Corp": 372.0 },
    "80": { "Day": 288.0, "Night": 363.0, "Corp": 396.0 },
    "85": { "Day": 305.0, "Night": 385.0, "Corp": 420.0 },
    "90": { "Day": 323.0, "Night": 407.0, "Corp": 443.0 },
    "95": { "Day": 340.0, "Night": 428.0, "Corp": 467.0 },
    "100": { "Day": 357.0, "Night": 450.0, "Corp": 491.0 },
    "105": { "Day": 374.0, "Night": 472.0, "Corp": 515.0 },
    "110": { "Day": 391.0, "Night": 494.0, "Corp": 539.0 },
    "115": { "Day": 408.0, "Night": 516.0, "Corp": 563.0 },
    "120": { "Day": 426.0, "Night": 538.0, "Corp": 587.0 },
    "125": { "Day": 443.0, "Night": 559.0, "Corp": 611.0 },
    "130": { "Day": 460.0, "Night": 581.0, "Corp": 634.0 },
    "135": { "Day": 477.0, "Night": 603.0, "Corp": 658.0 },
    "140": { "Day": 494.0, "Night": 625.0, "Corp": 682.0 },
    "145": { "Day": 511.0, "Night": 647.0, "Corp": 706.0 },
    "150": { "Day": 529.0, "Night": 669.0, "Corp": 730.0 },
    "155": { "Day": 546.0, "Night": 690.0, "Corp": 754.0 },
    "160": { "Day": 563.0, "Night": 712.0, "Corp": 778.0 },
    "165": { "Day": 580.0, "Night": 734.0, "Corp": 802.0 },
    "170": { "Day": 597.0, "Night": 756.0, "Corp": 826.0 },
    "175": { "Day": 615.0, "Night": 778.0, "Corp": 849.0 },
    "180": { "Day": 632.0, "Night": 800.0, "Corp": 873.0 },
    "185": { "Day": 649.0, "Night": 821.0, "Corp": 897.0 },
    "190": { "Day": 666.0, "Night": 843.0, "Corp": 921.0 },
    "195": { "Day": 683.0, "Night": 865.0, "Corp": 945.0 },
    "200": { "Day": 700.0, "Night": 887.0, "Corp": 969.0 },
    "205": { "Day": 718.0, "Night": 909.0, "Corp": 993.0 },
    "210": { "Day": 735.0, "Night": 931.0, "Corp": 1017.0 },
    "215": { "Day": 752.0, "Night": 953.0, "Corp": 1041.0 },
    "220": { "Day": 769.0, "Night": 974.0, "Corp": 1064.0 },
    "225": { "Day": 786.0, "Night": 996.0, "Corp": 1088.0 },
    "230": { "Day": 803.0, "Night": 1018.0, "Corp": 1112.0 },
    "235": { "Day": 821.0, "Night": 1040.0, "Corp": 1136.0 },
    "240": { "Day": 838.0, "Night": 1062.0, "Corp": 1160.0 },
    "245": { "Day": 855.0, "Night": 1084.0, "Corp": 1184.0 },
    "250": { "Day": 872.0, "Night": 1105.0, "Corp": 1208.0 },
    "255": { "Day": 889.0, "Night": 1127.0, "Corp": 1232.0 },
    "260": { "Day": 907.0, "Night": 1149.0, "Corp": 1256.0 },
    "265": { "Day": 924.0, "Night": 1171.0, "Corp": 1279.0 },
    "270": { "Day": 941.0, "Night": 1193.0, "Corp": 1303.0 },
    "275": { "Day": 958.0, "Night": 1215.0, "Corp": 1327.0 },
    "280": { "Day": 975.0, "Night": 1236.0, "Corp": 1351.0 },
    "285": { "Day": 992.0, "Night": 1258.0, "Corp": 1375.0 },
    "290": { "Day": 1010.0, "Night": 1280.0, "Corp": 1399.0 },
    "295": { "Day": 1027.0, "Night": 1302.0, "Corp": 1423.0 },
    "300": { "Day": 1044.0, "Night": 1324.0, "Corp": 1447.0 }
  },
  "tolls": {
    "None": 0,
    "North Western Sydney": 40,
    "Parramatta": 40,
    "Cammeray - North of Bridge": 40,
    "Sydney Central": 65,
    "Campbelltown": 75,
    "Penrith": 75,
    "Sydney Airport": 175
  }
}
